encode_8b_10b/8b10b/decode_8b10b.v
module decode (datain, dispin, dataout, dispout, code_err, disp_err) ;
  input [9:0]   datain ;
  input        dispin ;
  output [8:0]    dataout ;
  output    dispout ;
  output    code_err ;
  output    disp_err ;

  wire ai = datain[0] ;
  wire bi = datain[1] ;
  wire ci = datain[2] ;
  wire di = datain[3] ;
  wire ei = datain[4] ;
  wire ii = datain[5] ;
  wire fi = datain[6] ;
  wire gi = datain[7] ;
  wire hi = datain[8] ;
  wire ji = datain[9] ;

  wire aeqb = (ai & bi) | (!ai & !bi) ;
  wire ceqd = (ci & di) | (!ci & !di) ;
  wire p22 = (ai & bi & !ci & !di) |
         (ci & di & !ai & !bi) |
         ( !aeqb & !ceqd) ;
  wire p13 = ( !aeqb & !ci & !di) |
         ( !ceqd & !ai & !bi) ;
  wire p31 = ( !aeqb & ci & di) |
         ( !ceqd & ai & bi) ;

  wire p40 = ai & bi & ci & di ;
  wire p04 = !ai & !bi & !ci & !di ;

  wire disp6a = p31 | (p22 & dispin) ; // pos disp if p22 and was pos, or p31.
   wire disp6a2 = p31 & dispin ;  // disp is ++ after 4 bits
   wire disp6a0 = p13 & ! dispin ; // -- disp after 4 bits

  wire disp6b = (((ei & ii & ! disp6a0) | (disp6a & (ei | ii)) | disp6a2 |
          (ei & ii & di)) & (ei | ii | di)) ;

  // The 5B/6B decoding special cases where ABCDE != abcde

  wire p22bceeqi = p22 & bi & ci & (ei == ii) ;
  wire p22bncneeqi = p22 & !bi & !ci & (ei == ii) ;
  wire p13in = p13 & !ii ;
  wire p31i = p31 & ii ;
  wire p13dei = p13 & di & ei & ii ;
  wire p22aceeqi = p22 & ai & ci & (ei == ii) ;
  wire p22ancneeqi = p22 & !ai & !ci & (ei == ii) ;
  wire p13en = p13 & !ei ;
  wire anbnenin = !ai & !bi & !ei & !ii ;
  wire abei = ai & bi & ei & ii ;
  wire cdei = ci & di & ei & ii ;
  wire cndnenin = !ci & !di & !ei & !ii ;

  // non-zero disparity cases:
  wire p22enin = p22 & !ei & !ii ;
  wire p22ei = p22 & ei & ii ;
  //wire p13in = p12 & !ii ;
  //wire p31i = p31 & ii ;
  wire p31dnenin = p31 & !di & !ei & !ii ;
  //wire p13dei = p13 & di & ei & ii ;
  wire p31e = p31 & ei ;

  wire compa = p22bncneeqi | p31i | p13dei | p22ancneeqi | 
        p13en | abei | cndnenin ;
  wire compb = p22bceeqi | p31i | p13dei | p22aceeqi | 
        p13en | abei | cndnenin ;
  wire compc = p22bceeqi | p31i | p13dei | p22ancneeqi | 
        p13en | anbnenin | cndnenin ;
  wire compd = p22bncneeqi | p31i | p13dei | p22aceeqi |
        p13en | abei | cndnenin ;
  wire compe = p22bncneeqi | p13in | p13dei | p22ancneeqi | 
        p13en | anbnenin | cndnenin ;

  wire ao = ai ^ compa ;
  wire bo = bi ^ compb ;
  wire co = ci ^ compc ;
  wire do = di ^ compd ;
  wire eo = ei ^ compe ;

  wire feqg = (fi & gi) | (!fi & !gi) ;
  wire heqj = (hi & ji) | (!hi & !ji) ;
  wire fghj22 = (fi & gi & !hi & !ji) |
        (!fi & !gi & hi & ji) |
        ( !feqg & !heqj) ;
  wire fghjp13 = ( !feqg & !hi & !ji) |
         ( !heqj & !fi & !gi) ;
  wire fghjp31 = ( (!feqg) & hi & ji) |
         ( !heqj & fi & gi) ;

  wire dispout = (fghjp31 | (disp6b & fghj22) | (hi & ji)) & (hi | ji) ;

  wire ko = ( (ci & di & ei & ii) | ( !ci & !di & !ei & !ii) |
        (p13 & !ei & ii & gi & hi & ji) |
        (p31 & ei & !ii & !gi & !hi & !ji)) ;

  wire alt7 =   (fi & !gi & !hi & // 1000 cases, where disp6b is 1
         ((dispin & ci & di & !ei & !ii) | ko |
          (dispin & !ci & di & !ei & !ii))) |
        (!fi & gi & hi & // 0111 cases, where disp6b is 0
         (( !dispin & !ci & !di & ei & ii) | ko |
          ( !dispin & ci & !di & ei & ii))) ;

  wire k28 = (ci & di & ei & ii) | ! (ci | di | ei | ii) ;
  // k28 with positive disp into fghi - .1, .2, .5, and .6 special cases
  wire k28p = ! (ci | di | ei | ii) ;
  wire fo = (ji & !fi & (hi | !gi | k28p)) |
        (fi & !ji & (!hi | gi | !k28p)) |
        (k28p & gi & hi) |
        (!k28p & !gi & !hi) ;
  wire go = (ji & !fi & (hi | !gi | !k28p)) |
        (fi & !ji & (!hi | gi |k28p)) |
        (!k28p & gi & hi) |
        (k28p & !gi & !hi) ;
  wire ho = ((ji ^ hi) & ! ((!fi & gi & !hi & ji & !k28p) | (!fi & gi & hi & !ji & k28p) | 
                (fi & !gi & !hi & ji & !k28p) | (fi & !gi & hi & !ji & k28p))) |
        (!fi & gi & hi & ji) | (fi & !gi & !hi & !ji) ;

  wire disp6p = (p31 & (ei | ii)) | (p22 & ei & ii) ;
  wire disp6n = (p13 & ! (ei & ii)) | (p22 & !ei & !ii) ;
  wire disp4p = fghjp31 ;
  wire disp4n = fghjp13 ;

  assign code_err = p40 | p04 | (fi & gi & hi & ji) | (!fi & !gi & !hi & !ji) |
            (p13 & !ei & !ii) | (p31 & ei & ii) | 
            (ei & ii & fi & gi & hi) | (!ei & !ii & !fi & !gi & !hi) | 
            (ei & !ii & gi & hi & ji) | (!ei & ii & !gi & !hi & !ji) |
            (!p31 & ei & !ii & !gi & !hi & !ji) |
            (!p13 & !ei & ii & gi & hi & ji) |
            (((ei & ii & !gi & !hi & !ji) | 
              (!ei & !ii & gi & hi & ji)) &
             ! ((ci & di & ei) | (!ci & !di & !ei))) |
            (disp6p & disp4p) | (disp6n & disp4n) |
            (ai & bi & ci & !ei & !ii & ((!fi & !gi) | fghjp13)) |
            (!ai & !bi & !ci & ei & ii & ((fi & gi) | fghjp31)) |
            (fi & gi & !hi & !ji & disp6p) |
            (!fi & !gi & hi & ji & disp6n) |
            (ci & di & ei & ii & !fi & !gi & !hi) |
            (!ci & !di & !ei & !ii & fi & gi & hi) ;

  assign dataout = {ko, ho, go, fo, eo, do, co, bo, ao} ;

  // my disp err fires for any legal codes that violate disparity, may fire for illegal codes
   assign disp_err = ((dispin & disp6p) | (disp6n & !dispin) |
              (dispin & !disp6n & fi & gi) |
              (dispin & ai & bi & ci) |
              (dispin & !disp6n & disp4p) |
              (!dispin & !disp6p & !fi & !gi) |
              (!dispin & !ai & !bi & !ci) |
              (!dispin & !disp6p & disp4n) |
              (disp6p & disp4p) | (disp6n & disp4n)) ;

endmodule

encode_8b_10b/8b10b/encode_8b10b.v
module encode (
       input [8:0]   datain,
       input         dispin, // 0 = 负位移; 1 = 正位移
       output [9:0]  dataout, 
       output        dispout
) ;
  wire ai = datain[0] ;
  wire bi = datain[1] ;
  wire ci = datain[2] ;
  wire di = datain[3] ;
  wire ei = datain[4] ;
  wire fi = datain[5] ;
  wire gi = datain[6] ;
  wire hi = datain[7] ;
  wire ki = datain[8] ;


  wire l22 = (ai & bi & !ci & !di) | (ci & di & !ai & !bi) | ( (ai^bi) & (ci^di)) ; // l22 逻辑条件
  wire l40 = ai & bi & ci & di ; // l40 逻辑条件
  wire l04 = !ai & !bi & !ci & !di ; // l04 逻辑条件
  wire l13 = ( (ai ^ bi) & !ci & !di) | ( (ci ^ di) & !ai & !bi) ; // l13 逻辑条件
  wire l31 = ( (ai ^ bi) & ci & di) | ( (ci ^ di) & ai & bi) ; // l31 逻辑条件

  /*----------------- 5B/6B 编码 --------------------*/

  wire ao = ai ; // 输出 a
  wire bo = (bi & !l40) | l04 ; // 输出 b
  wire co = l04 | ci | (ei & di & !ci & !bi & !ai) ; // 输出 c
  wire do = di & ! (ai & bi & ci) ; // 输出 d
  wire eo = (ei | l13) & ! (ei & di & !ci & !bi & !ai) ; // 输出 e
  wire io = (l22 & !ei) |
        (ei & !di & !ci & !(ai&bi)) |  // D16, D17, D18
        (ei & l40) |
        (ki & ei & di & ci & !bi & !ai) | // K.28
        (ei & !di & ci & !bi & !ai) ; // 输出 i

  // pds16 表示假设 d-1 为 + 来获得编码值的情况
  wire pd1s6 = (ei & di & !ci & !bi & !ai) | (!ei & !l22 & !l31) ;
  // nds16 表示假设 d-1 为 - 来获得编码值的情况
  wire nd1s6 = ki | (ei & !l22 & !l13) | (!ei & !di & ci & bi & ai) ;

  // ndos6 是 pds16 情况，其中 d-1 为 + 产生负位移输出
  wire ndos6 = pd1s6 ;
  // pdos6 是 nds16 情况，其中 d-1 为 - 产生正位移输出
  wire pdos6 = ki | (ei & !l22 & !l13) ;

  // 某些 Dx.7 和所有 Kx.7 情况导致运行长度为 5，除非使用替代编码（称为 Dx.A7，正常为 Dx.P7）
  // 特别是 D11, D13, D14, D17, D18, D19.
  wire alt7 = fi & gi & hi & (ki | (dispin ? (!ei & di & l31) : (ei & !di & l13))) ;
  

  /*-----------------------------3B/4B 编码-----------------------------*/
  wire fo = fi & ! alt7 ; // 输出 f
  wire go = gi | (!fi & !gi & !hi) ; // 输出 g
  wire ho = hi ; // 输出 h
  wire jo = (!hi & (gi ^ fi)) | alt7 ; // 输出 j

  // nd1s4 是假设 d-1 为 - 来获得编码值的情况
  wire nd1s4 = fi & gi ;
  // pd1s4 是假设 d-1 为 + 来获得编码值的情况
  wire pd1s4 = (!fi & !gi) | (ki & ( fi ^ gi)) ;

  // ndos4 是 pd1s4 情况，其中 d-1 为 + 产生负位移输出
  wire ndos4 = (!fi & !gi) ;
  // pdos4 是 nd1s4 情况，其中 d-1 为 - 产生正位移输出
  wire pdos4 = fi & gi & hi ;

  // 只有合法的 K 代码是 K28.0->.7, K23/27/29/30.7
  //    K28.0->7 是 ei=di=ci=1, bi=ai=0
  //    K23 是 10111
  //    K27 是 11011
  //    K29 是 11101
  //    K30 是 11110 - 所以 K23/27/29/30 是 ei & l31
  wire illegalk = ki & 
          (ai | bi | !ci | !di | !ei) & // 不是 K28.0->7
          (!fi | !gi | !hi | !ei | !l31) ; // 不是 K23/27/29/30.7

  // 现在确定是否需要进行补码运算
  // 如果前一个位移为 - 且 pd1s6 被设置，或 + 且 nd1s6 被设置则补码
  wire compls6 = (pd1s6 & !dispin) | (nd1s6 & dispin) ;

  // 5B/6B 的位移输出是 disp in 与 pdso6 和 ndso6 的异或
  // pds16 表示假设 d-1 为 + 来获得编码值的情况
  // ndos6 是 d-1 为 + 产生负位移输出的情况
  // nds16 表示假设 d-1 为 - 来获得编码值的情况
  // pdos6 是 d-1 为 - 产生正位移输出的情况
  // 在所有 ndis16 情况下，位移翻转，并且所有但一个 nds16 情况

  wire disp6 = dispin ^ (ndos6 | pdos6) ;

  wire compls4 = (pd1s4 & !disp6) | (nd1s4 & disp6) ;
  assign dispout = disp6 ^ (ndos4 | pdos4) ; // 输出位移

  assign dataout = {(jo ^ compls4), (ho ^ compls4),
            (go ^ compls4), (fo ^ compls4),
            (io ^ compls6), (eo ^ compls6),
            (do ^ compls6), (co ^ compls6),
            (bo ^ compls6), (ao ^ compls6)} ; // 输出数据

endmodule

encode_8b_10b/8b10b/testbench_8b10b.v
`timescale 1ns / 1ns
module test_8b10b ;
   reg [29:0]    code8b10b [0:267] ;
   reg [8:0]     testin ;
   reg         dispin ;
   reg [10:0]     i ;
   wire [9:0]     testout ;
   wire     dispout, decodedisp, decodeerr, disperr ;
   wire [8:0]     decodeout ;
   // My data file is 30 columns. Column 1 becomes [29], 2 becomes [28], etc..
   // code[0] is last Column (30)
   // First column, [29] is K indication
   // columns 2:9, [28:21], are data byte, aka 'm' and 'n' of Dm.n
   // columns 10:19, [20:11] are 10b symbol if starting disparity was negative, 0
   // columns 20:29, [10:1] are 10b symbol if starting disparity was positive, 1
   // column 30, [0], is a 1 if symbol results in a disparity flip
   //   0 for a balanced symbol (5 '1's, 5 '0's).

   wire [29:0]     code = code8b10b[i] ;
   wire [9:0]     expect_0_disp = {code[11], code[12], code[13], code[14], code[15],
                 code[16], code[17], code[18], code[19], code[20]} ;
   wire [9:0]     expect_1_disp = {code[1], code[2], code[3], code[4], code[5],
                 code[6], code[7], code[8], code[9], code[10]} ;

   reg [1023:0] legal ;  // mark every used 10b symbol as legal, leave rest marked as not
   reg [2047:0] okdisp ; // now mark every used combination of symbol and starting disparity
   reg [8:0]     mapcode [1023:0] ;
   reg [10:0]     codedisp0, codedisp1 ;
   reg [9:0]     decodein ;
   reg         decdispin ;
   integer     errors ;

   encode DUTE (testin, dispin, testout, dispout) ;
   decode DUTD (decodein, decdispin, decodeout, decodedisp, decodeerr, disperr) ;

   always @ (code) testin = code[29:21] ;

   initial begin 
      errors = 0 ;
      $readmemb ("H:/FPGA_basicproject/encode_8b_10b/8b10b/8b10b_a.mem", code8b10b) ;
      //$vcdpluson ;
      $dumpvars (0);
      $display ("\n\nFirst, test by trying all 268 (256 Dx.y and 12 Kx.y)") ;
      $display ("valid inputs, with both + and - starting disparity.");
      $display ("We check that the encoder output and ending disparity is correct.");
      $display ("We also check that the decoder matches.");
      for (i = 0 ; i < 268 ; i = i + 1) begin
     // testin = code[29:21] ;
     dispin = 0 ;
     #1
       decodein = testout ;
     decdispin = dispin ;
     #1
//       $display ("%b %b %b %b *%b*", dispin, testin, testout, {dispout, DUTD.disp6a, DUTD.disp6a2, DUTD.disp6a0, DUTD.disp6a2}, decodeout,, decodedisp,, DUTD.k28,, DUTD.disp6b) ;
     if (testout != expect_0_disp) 
       $display ("bad code0 %b %b %b %b %b", dispin, testin,  dispout, testout, expect_0_disp) ;
     if (dispout != (dispin ^ code[0]))
       $display ("bad disp0 %b %b %b %b %b", dispin, testin, dispout, testout, (dispin ^ code[0])) ;
     if (0 != (9'b1_1111_1111 & (testin ^ decodeout)))
       $display ("diff in abcdefghk decode, %b %b %b %b %b", dispin, testin,  dispout, testout, decodeout) ;
     if (decodedisp != dispout)
       $display ("diff in decoder disp out, %b %b %b %b %b", dispin, testin,  dispout, testout, decodeout) ;
     if (decodeerr) $display ("decode error asserted improperly, %b %b %b %b %b", dispin, testin,  dispout, testout, decodeout) ;
     if ((testout != expect_0_disp) | decodeerr |
         (dispout != (dispin ^ code[0])) | (decodedisp != dispout))
       errors = errors + 1 ;

     dispin = 1 ;
     #1
     decodein = testout ;
     decdispin = dispin ;
     #1
//       $display ("%b %b %b %b *%b*", dispin, testin, testout, {dispout, DUTD.disp6a, DUTD.disp6a2, DUTD.disp6a0, DUTD.disp6a2, DUTD.fghjp31, DUTD.feqg, DUTD.heqj, DUTD.fghj22, DUTD.fi, DUTD.gi, DUTD.hi, DUTD.ji, DUTD.dispout}, decodeout,, decodedisp,, DUTD.k28,, DUTD.disp6b) ;
     if (testout != expect_1_disp) 
       $display ("bad code1 %b %b %b %b %b", dispin, testin, dispout, testout, expect_1_disp) ;
     if (dispout != (dispin ^ code[0]))
       $display ("bad disp1 %b %b %b %b %b", dispin, testin,  dispout, testout, (dispin ^ code[0])) ;
     if (0 != (9'b1_1111_1111 & (testin ^ decodeout)))
       $display ("diff in abcdefghk decode, %b %b %b %b %b", dispin, testin,  dispout, testout, decodeout) ;
     if (decodedisp != dispout)
       $display ("diff in decoder disp out, %b %b %b %b %b", dispin, testin,  dispout, testout, decodeout) ;
     if (decodeerr) $display ("decode error asserted improperly, %b %b %b %b %b", dispin, testin,  dispout, testout, decodeout) ;
     if ((testout != expect_1_disp) | decodeerr |
         (dispout != (dispin ^ code[0])) | (decodedisp != dispout))
       errors = errors + 1 ;
      end
      $display ("%d errors in that testing.\n", errors) ;

      // Now, having verified all legal codes, lets run some illegal codes
      // at the decoder... how to figure illegal codes ?  2048 possible cases,
      // lets mark the OK ones...
      legal = 0 ;
      okdisp = 0 ;
      for (i = 0 ; i < 268 ; i = i + 1) begin
     #1
//       $display ("i=%d: %b %b %d %d %x %x", i, expect_0_disp, expect_1_disp, expect_0_disp, expect_1_disp, expect_0_disp, expect_1_disp) ;
     legal[expect_0_disp] = 1 ;
     legal[expect_1_disp] = 1 ;
     codedisp0 = expect_0_disp ;
     codedisp1 = {1'b1, expect_1_disp} ;
     okdisp[codedisp0] = 1 ;
     okdisp[codedisp1] = 1 ;
     mapcode[expect_0_disp] = code[29:21] ;
     mapcode[expect_1_disp] = code[29:21] ;
      end

      $display ("Now lets test all (legal and illegal) codes into the decoder.");
      $display ("checking all possible decode inputs") ;
      for (i = 0 ; i < 1024 ; i = i + 1) begin
     decodein = i ;
     decdispin = 0 ;
     codedisp1 = 1024 | i ;
     #1
     if (((legal[i] == 0) & (decodeerr != 1)) |
         (legal[i] & (mapcode[i] != decodeout)) |
         (legal[i] & (disperr != !okdisp[i])))
       $display ("10b:%b start disp:%b 8b:%b end disp:%b codevio:%b dispvio:%b known code:%b used disp:", 
             decodein, decdispin, decodeout, decodedisp, decodeerr, disperr, legal[i], okdisp[i]) ;
     if ((legal[i] == 0) & (decodeerr != 1)) $display ("ERR: decoderr should be 1") ;
     if (legal[i] & (mapcode[i] != decodeout)) $display ("ERR: decode output incorrect") ;
     if (legal[i] & (disperr != 1) & !okdisp[i]) $display ("ERR: disp err should be asserted") ;
     else if (legal[i] & (disperr != 0) & okdisp[i])
       $display ("ERR: disp err should not be asserted") ;

     if (((legal[i] == 0) & (decodeerr != 1)) |
         (legal[i] & !disperr & !okdisp[i]) |
         (legal[i] & (mapcode[i] != decodeout)) |
         (legal[i] & disperr & okdisp[i]))
       errors = errors + 1 ;

     decdispin = 1 ;
     #1
     if (((legal[i] == 0) & (decodeerr != 1)) |
         (legal[i] & (mapcode[i] != decodeout)) |
         (legal[i] & (disperr != !okdisp[i|1024])))
       $display ("10b:%b start disp:%b 8b:%b end disp:%b codevio:%b dispvio:%b known code:%b used disp:", 
             decodein, decdispin, decodeout, decodedisp, decodeerr, disperr, legal[i], okdisp[i|1024]) ;
     if ((legal[i] == 0) & (decodeerr != 1)) $display ("ERR: decoderr should be 1") ;
     if (legal[i] & (mapcode[i] != decodeout)) $display ("ERR: decode output incorrect") ;
     if (legal[i] & (disperr != 1) & !okdisp[i|1024]) $display ("ERR: disp err should be asserted") ;
     else if (legal[i] & (disperr != 0) & okdisp[i|1024])
       $display ("ERR: disp err should not be asserted") ;
     if (((legal[i] == 0) & (decodeerr != 1)) |
         (legal[i] & !disperr & !okdisp[i|1024]) |
         (legal[i] & (mapcode[i] != decodeout)) |
         (legal[i] & disperr & okdisp[i|1024]))
       errors = errors + 1 ;
      end // for (i = 0 ; i < 1024 ; i = i + 1)

      $display ("\nDone testing decoder.\n") ;
      $display ("Total error count: %d", errors);
      if (errors == 0) $display ("Congratulations!\n");
      $finish ;
   end // initial begin

endmodule

encode_8b_10b/8b10b/project/project_8b10b/project_8b10b.sim/sim_1/behav/xsim/dump.vcd
$date
   Sat Nov  2 18:32:54 2024
$end
$version
  2019.2
$end
$timescale
  1ps
$end
$scope module test_8b10b $end
$var reg 9 ! testin [8:0] $end
$var reg 1 " dispin $end
$var reg 11 # i [10:0] $end
$var wire 10 $ testout [9:0] $end
$var wire 1 % dispout $end
$var wire 1 & decodedisp $end
$var wire 1 ' decodeerr $end
$var wire 1 ( disperr $end
$var wire 9 ) decodeout [8:0] $end
$var wire 30 * code [29:0] $end
$var wire 10 + expect_0_disp [9:0] $end
$var wire 10 , expect_1_disp [9:0] $end
$var reg 1024 - legal [1023:0] $end
$var reg 2048 . okdisp [2047:0] $end
$var reg 11 / codedisp0 [10:0] $end
$var reg 11 0 codedisp1 [10:0] $end
$var reg 10 1 decodein [9:0] $end
$var reg 1 2 decdispin $end
$var integer 32 3 errors $end
$scope module DUTE $end
$var wire 9 4 datain [8:0] $end
$var wire 1 5 dispin $end
$var wire 10 $ dataout [9:0] $end
$var wire 1 % dispout $end
$var wire 1 6 ai $end
$var wire 1 7 bi $end
$var wire 1 8 ci $end
$var wire 1 9 di $end
$var wire 1 : ei $end
$var wire 1 ; fi $end
$var wire 1 < gi $end
$var wire 1 = hi $end
$var wire 1 > ki $end
$var wire 1 ? l22 $end
$var wire 1 @ l40 $end
$var wire 1 A l04 $end
$var wire 1 B l13 $end
$var wire 1 C l31 $end
$var wire 1 D ao $end
$var wire 1 E bo $end
$var wire 1 F co $end
$var wire 1 G do $end
$var wire 1 H eo $end
$var wire 1 I io $end
$var wire 1 J pd1s6 $end
$var wire 1 K nd1s6 $end
$var wire 1 L ndos6 $end
$var wire 1 M pdos6 $end
$var wire 1 N alt7 $end
$var wire 1 O fo $end
$var wire 1 P go $end
$var wire 1 Q ho $end
$var wire 1 R jo $end
$var wire 1 S nd1s4 $end
$var wire 1 T pd1s4 $end
$var wire 1 U ndos4 $end
$var wire 1 V pdos4 $end
$var wire 1 W illegalk $end
$var wire 1 X compls6 $end
$var wire 1 Y disp6 $end
$var wire 1 Z compls4 $end
$upscope $end
$scope module DUTD $end
$var wire 10 [ datain [9:0] $end
$var wire 1 \ dispin $end
$var wire 9 ) dataout [8:0] $end
$var wire 1 ' code_err $end
$var wire 1 ( disp_err $end
$var wire 1 ] ai $end
$var wire 1 ^ bi $end
$var wire 1 _ ci $end
$var wire 1 ` di $end
$var wire 1 a ei $end
$var wire 1 b ii $end
$var wire 1 c fi $end
$var wire 1 d gi $end
$var wire 1 e hi $end
$var wire 1 f ji $end
$var wire 1 g aeqb $end
$var wire 1 h ceqd $end
$var wire 1 i p22 $end
$var wire 1 j p13 $end
$var wire 1 k p31 $end
$var wire 1 l p40 $end
$var wire 1 m p04 $end
$var wire 1 n disp6a $end
$var wire 1 o disp6a2 $end
$var wire 1 p disp6a0 $end
$var wire 1 q disp6b $end
$var wire 1 r p22bceeqi $end
$var wire 1 s p22bncneeqi $end
$var wire 1 t p13in $end
$var wire 1 u p31i $end
$var wire 1 v p13dei $end
$var wire 1 w p22aceeqi $end
$var wire 1 x p22ancneeqi $end
$var wire 1 y p13en $end
$var wire 1 z anbnenin $end
$var wire 1 { abei $end
$var wire 1 | cdei $end
$var wire 1 } cndnenin $end
$var wire 1 ~ p22enin $end
$var wire 1 !! p22ei $end
$var wire 1 "! p31dnenin $end
$var wire 1 #! p31e $end
$var wire 1 $! compa $end
$var wire 1 %! compb $end
$var wire 1 &! compc $end
$var wire 1 '! compd $end
$var wire 1 (! compe $end
$var wire 1 )! ao $end
$var wire 1 *! bo $end
$var wire 1 +! co $end
$var wire 1 ,! do $end
$var wire 1 -! eo $end
$var wire 1 .! feqg $end
$var wire 1 /! heqj $end
$var wire 1 0! fghj22 $end
$var wire 1 1! fghjp13 $end
$var wire 1 2! fghjp31 $end
$var wire 1 & dispout $end
$var wire 1 3! ko $end
$var wire 1 4! alt7 $end
$var wire 1 5! k28 $end
$var wire 1 6! k28p $end
$var wire 1 7! fo $end
$var wire 1 8! go $end
$var wire 1 9! ho $end
$var wire 1 :! disp6p $end
$var wire 1 ;! disp6n $end
$var wire 1 <! disp4p $end
$var wire 1 =! disp4n $end
$upscope $end
$upscope $end
$enddefinitions $end
#0
$dumpvars
b0 !
x!!
0"
x"!
b0 #
x#!
b10111001 $
x$!
0%
x%!
x&
x&!
x'
x'!
x(
x(!
bx )
x)!
b100111010001100010110 *
x*!
b10111001 +
x+!
b1101000110 ,
x,!
bx -
x-!
bx .
x.!
bx /
x/!
bx 0
x0!
bx 1
x1!
x2
x2!
b0 3
x3!
b0 4
x4!
05
x5!
06
x6!
07
x7!
08
x8!
09
x9!
0:
x:!
0;
x;!
0<
x<!
0=
x=!
0>
0?
0@
1A
0B
0C
0D
1E
1F
0G
0H
0I
1J
0K
1L
0M
0N
0O
1P
0Q
0R
0S
1T
1U
0V
0W
1X
1Y
0Z
bx [
x\
x]
x^
x_
x`
xa
xb
xc
xd
xe
xf
xg
xh
xi
xj
xk
xl
xm
xn
xo
xp
xq
xr
xs
xt
xu
xv
xw
xx
xy
xz
x{
x|
x}
x~
$end
#1000
1!!
0"!
0#!
1$!
0%!
0&
0&!
0'
1'!
0(
1(!
b0 )
0)!
0*!
0+!
0,!
0-!
0.!
1/!
00!
b10111001 1
11!
02
02!
03!
04!
05!
06!
07!
08!
09!
1:!
0;!
0<!
1=!
b10111001 [
0\
1]
0^
0_
1`
1a
1b
0c
1d
0e
0f
0g
0h
1i
0j
0k
0l
0m
0n
0o
0p
1q
0r
1s
0t
0u
0v
0w
0x
0y
0z
0{
0|
0}
0~
#2000
1"
b1101000110 $
1%
15
0N
0X
0Y
1Z
#3000
0!!
0"!
0#!
0$!
1%!
1&
1&!
0'
0'!
0(
0(!
b0 )
0)!
0*!
0+!
0,!
0-!
0.!
1/!
00!
b1101000110 1
01!
12
12!
03!
04!
05!
06!
07!
08!
09!
0:!
1;!
1<!
0=!
b1101000110 [
1\
0]
1^
1_
0`
0a
0b
1c
0d
1e
1f
0g
0h
1i
0j
0k
0l
0m
1n
0o
0p
0q
1r
0s
0t
0u
0v
0w
0x
0y
0z
0{
0|
0}
1~
#4000
b1 !
0"
b1 #
b10101110 $
0%
b1011101010010001010110 *
b10101110 +
b1101010001 ,
b1 4
05
16
0?
0@
0A
1B
0C
1D
0E
0F
0G
1H
0I
1J
0K
0M
0N
0W
1X
1Y
0Z
#5000
0!!
0"!
0#!
1$!
1%!
0&
1&!
0'
1'!
0(
b1 )
1)!
0,!
0.!
1/!
00!
b10101110 1
11!
02
02!
03!
04!
05!
06!
07!
08!
09!
1:!
0;!
0<!
1=!
b10101110 [
0\
1`
1b
0c
1d
0e
0f
1h
0i
0j
1k
0l
0m
1n
0o
0p
1q
0r
0s
0t
1u
0v
0w
0x
0z
0{
0|
0}
0~
#6000
1"
b1101010001 $
1%
15
0N
0X
0Y
1Z
#7000
0!!
0"!
0#!
0$!
0%!
1&
0&!
0'
0'!
0(
1(!
b1 )
1)!
0*!
0+!
0,!
0-!
0.!
1/!
00!
b1101010001 1
01!
12
12!
03!
04!
05!
06!
07!
08!
09!
0:!
1;!
1<!
0=!
b1101010001 [
1\
1]
0^
0_
0`
1a
0b
1c
0d
1e
1f
0g
1h
0i
1j
0k
0l
0m
0n
0o
0p
0q
0r
0s
1t
0u
0v
0w
0x
0y
0z
0{
0|
0}
0~
#8000
b10 !
0"
b10 #
b10101101 $
0%
b10101101010001001010110 *
b10101101 +
b1101010010 ,
b10 4
05
06
17
0?
0@
0A
1B
0C
0D
1E
0F
0G
1H
0I
1J
0K
0N
0W
1X
1Y
0Z
#9000
0!!
0"!
0#!
1$!
1%!
0&
1&!
0'
1'!
0(
0(!
b10 )
0)!
1*!
0+!
0,!
0-!
0.!
1/!
00!
b10101101 1
11!
02
02!
03!
04!
05!
06!
07!
08!
09!
1:!
0;!
0<!
1=!
b10101101 [
0\
1_
1`
0a
1b
0c
1d
0e
0f
1h
0i
0j
1k
0l
0m
1n
0o
0p
1q
0r
0s
0t
1u
0v
0w
0x
0y
0z
0{
0|
0}
0~
#10000
1"
b1101010010 $
1%
15
0N
0X
0Y
1Z
#11000
0!!
0"!
0#!
0$!
0%!
1&
0&!
0'
0'!
0(
1(!
b10 )
0)!
1*!
0+!
0,!
0-!
0.!
1/!
00!
b1101010010 1
01!
12
12!
03!
04!
05!
06!
07!
08!
09!
0:!
1;!
1<!
0=!
b1101010010 [
1\
0]
1^
0_
0`
1a
0b
1c
0d
1e
1f
0g
1h
0i
1j
0k
0l
0m
0n
0o
0p
0q
0r
0s
1t
0u
0v
0w
0x
0y
0z
0{
0|
0}
0~
#12000
b11 !
0"
b11 #
b1101100011 $
1%
b11110001101111000101001 *
b1101100011 +
b10100011 ,
b11 4
05
16
1?
0@
0A
0B
0C
1D
0F
0G
0H
1I
0J
0K
0L
0M
0N
0W
0X
0Y
1Z
#13000
0!!
0"!
0#!
0'
0(
0(!
b11 )
1)!
0-!
b1101100011 1
02
03!
04!
05!
06!
0:!
0;!
b1101100011 [
0\
1]
0a
1b
1g
1i
0j
0k
0l
0m
0n
0o
0p
0q
0r
0s
0t
0u
0v
0w
0x
0y
0z
0{
0|
0}
0~
#14000
1"
b10100011 $
0%
15
0N
0X
1Y
0Z
#15000
0&
0'
0(
0.!
1/!
00!
b10100011 1
11!
12
02!
03!
04!
07!
08!
09!
0<!
1=!
b10100011 [
1\
0c
1d
0e
0f
1n
0o
0p
1q
#16000
b100 !
0"
b100 #
b10101011 $
0%
b100110101010000101010110 *
b10101011 +
b1101010100 ,
b100 4
05
06
07
18
0?
0@
0A
1B
0C
0D
0E
1F
0G
1H
0I
1J
0K
1L
0M
0N
0W
1X
1Y
0Z
#17000
0!!
0"!
0#!
1$!
1%!
0&
1&!
0'
1'!
0(
b100 )
0)!
0*!
1+!
0,!
b10101011 1
02
03!
04!
05!
06!
1:!
0;!
b10101011 [
0\
1`
0h
0i
0j
1k
0l
0m
1n
0o
0p
1q
0r
0s
1u
0v
0w
0x
0|
0}
0~
#18000
1"
b1101010100 $
1%
15
0N
0X
0Y
1Z
#19000
0!!
0"!
0#!
0$!
0%!
1&
0&!
0'
0'!
0(
1(!
b100 )
0)!
0*!
1+!
0,!
0-!
0.!
1/!
00!
b1101010100 1
01!
12
12!
03!
04!
05!
06!
07!
08!
09!
0:!
1;!
1<!
0=!
b1101010100 [
1\
0]
0^
1_
0`
1a
0b
1c
0d
1e
1f
1g
0h
0i
1j
0k
0l
0m
0n
0o
0p
0q
0r
0s
1t
0u
0v
0w
0x
0y
0z
0{
0|
0}
0~
#20000
b101 !
0"
b101 #
b1101100101 $
1%
b101101001101110100101001 *
b1101100101 +
b10100101 ,
b101 4
05
16
1?
0@
0A
0B
0C
1D
1F
0G
0H
1I
0J
0K
0L
0M
0N
0W
0X
0Y
1Z
#21000
0!!
0"!
0#!
0'
0(
0(!
b101 )
1)!
0-!
b1101100101 1
02
03!
04!
05!
06!
0:!
0;!
b1101100101 [
0\
1]
0a
1b
0g
1i
0j
0k
0l
0m
0n
0o
0p
0q
0r
0s
0t
0u
0v
0w
0x
0y
0z
0{
0|
0}
0~
